geomatica/__init__.py
geomatica-1.3.3.dist-info/METADATA
geomatica-1.3.3.dist-info/WHEEL
geomatica-1.3.3.dist-info/top_level.txt
geomatica-1.3.3.dist-info/RECORD
