Metadata-Version: 2.1
Name: geomatica
Version: 1.3.3
Summary: Geometric Algebra in Python
Home-page: https://github.com/svntythsnd/geomatica
Author: slycedf
License: MIT
Keywords: geometric algebra GA Clifford multivector mathematics physics bivector wedge
Classifier: Development Status :: 5 - Production/Stable
Classifier: Programming Language :: Python :: 3
Classifier: Programming Language :: Python :: 3.10
Classifier: Programming Language :: Python :: 3.11
Classifier: License :: OSI Approved :: MIT License
Classifier: Intended Audience :: Science/Research
Classifier: Intended Audience :: Education
Classifier: Topic :: Scientific/Engineering :: Mathematics
Classifier: Topic :: Software Development :: Libraries
Classifier: Operating System :: OS Independent
Requires-Python: >=3.10
